MetabaseClient/Client.py
MetabaseClient/__init__.py
MetabaseClient/Addon/Migrate.py
MetabaseClient/Addon/SearchCard.py
MetabaseClient/Addon/__init__.py
MetabaseClient/Core/Authenticate.py
MetabaseClient/Core/Card.py
MetabaseClient/Core/Dashboard.py
MetabaseClient/Core/__init__.py
MetabaseClient-0.1.0.dist-info/LICENSE
MetabaseClient-0.1.0.dist-info/LICENSE-old
MetabaseClient-0.1.0.dist-info/METADATA
MetabaseClient-0.1.0.dist-info/WHEEL
MetabaseClient-0.1.0.dist-info/top_level.txt
MetabaseClient-0.1.0.dist-info/RECORD
