Metadata-Version: 2.1
Name: MetabaseClient
Version: 0.1.0
Summary: Metabase python wrapper is built upon Metabase restful API to help its users in extending features and adding more capability.
Home-page: https://github.com/vangiex/metabaseclient
Author: Rahul Rathi
Author-email: VanGiex.RR@Gmail.com
License: UNKNOWN
Platform: UNKNOWN
